CHANGELOG.md
MANIFEST.in
README.md
setup.cfg
setup.py
versioneer.py
src/libreflow/__init__.py
src/libreflow.extensions.anpo.scene_builder.egg-info/PKG-INFO
src/libreflow.extensions.anpo.scene_builder.egg-info/SOURCES.txt
src/libreflow.extensions.anpo.scene_builder.egg-info/dependency_links.txt
src/libreflow.extensions.anpo.scene_builder.egg-info/top_level.txt
src/libreflow/extensions/__init__.py
src/libreflow/extensions/anpo/__init__.py
src/libreflow/extensions/anpo/scene_builder/__init__.py
src/libreflow/extensions/anpo/scene_builder/_version.py
src/libreflow/extensions/anpo/scene_builder/build_utils.py
src/libreflow/extensions/anpo/scene_builder/error_handlers.py
src/libreflow/extensions/anpo/scene_builder/scripts/__init__.py
src/libreflow/extensions/anpo/scene_builder/scripts/setup_comp.jsx